huaweicloudsdkasm/__init__.py
huaweicloudsdkasm/v1/__init__.py
huaweicloudsdkasm/v1/asm_async_client.py
huaweicloudsdkasm/v1/asm_client.py
huaweicloudsdkasm/v1/model/__init__.py
huaweicloudsdkasm/v1/model/access_logging.py
huaweicloudsdkasm/v1/model/aom.py
huaweicloudsdkasm/v1/model/create_mesh_request.py
huaweicloudsdkasm/v1/model/create_mesh_response.py
huaweicloudsdkasm/v1/model/delete_mesh_request.py
huaweicloudsdkasm/v1/model/delete_mesh_response.py
huaweicloudsdkasm/v1/model/field_selector.py
huaweicloudsdkasm/v1/model/injection_config.py
huaweicloudsdkasm/v1/model/installation_config.py
huaweicloudsdkasm/v1/model/list_meshes_request.py
huaweicloudsdkasm/v1/model/list_meshes_response.py
huaweicloudsdkasm/v1/model/lts_config.py
huaweicloudsdkasm/v1/model/mesh.py
huaweicloudsdkasm/v1/model/mesh_cluster.py
huaweicloudsdkasm/v1/model/mesh_config.py
huaweicloudsdkasm/v1/model/mesh_extend_params.py
huaweicloudsdkasm/v1/model/mesh_metadata.py
huaweicloudsdkasm/v1/model/mesh_spec.py
huaweicloudsdkasm/v1/model/mesh_status.py
huaweicloudsdkasm/v1/model/mesh_tags.py
huaweicloudsdkasm/v1/model/metric.py
huaweicloudsdkasm/v1/model/proxy_config.py
huaweicloudsdkasm/v1/model/selector.py
huaweicloudsdkasm/v1/model/show_mesh_request.py
huaweicloudsdkasm/v1/model/show_mesh_response.py
huaweicloudsdkasm/v1/model/telemetry_config.py
huaweicloudsdkasm/v1/model/tracing.py
huaweicloudsdkasm/v1/model/tracing_extension_provider.py
huaweicloudsdkasm/v1/model/zipkin_tracing_provider.py
huaweicloudsdkasm/v1/region/__init__.py
huaweicloudsdkasm/v1/region/asm_region.py
huaweicloudsdkasm-3.1.184.dist-info/METADATA
huaweicloudsdkasm-3.1.184.dist-info/WHEEL
huaweicloudsdkasm-3.1.184.dist-info/licenses/LICENSE
huaweicloudsdkasm-3.1.184.dist-info/RECORD
